[{"lcs":{"index":"M217BA-0001-2020-01-21-09:01:00","recordTimestamp":{"recordDate":"2020-01-20","recordTime":"07:31:06","recordEpoch":"1579534266"},"location":{"travelFlowDirection":"East","begin":{"beginDistrict":"5","beginLocationName":"Sandspit Road","beginFreeFormDescription":"with ramp","beginNearbyPlace":"Goleta","beginLongitude":"-119.832491","beginLatitude":"34.418770","beginElevation":"9","beginDirection":"","beginCounty":"Santa Barbara","beginRoute":"SR-217","beginRouteSuffix":"","beginPostmilePrefix":"","beginPostmile":"0.94","beginAlignment":"","beginMilepost":"0.48"},"end":{"endDistrict":"5","endLocationName":"Route 101","endFreeFormDescription":"","endNearbyPlace":"Santa Barbara","endLongitude":"-119.808635","endLatitude":"34.441932","endElevation":"88","endDirection":"","endCounty":"Santa Barbara","endRoute":"SR-217","endRouteSuffix":"","endPostmilePrefix":"","endPostmile":"2.99","endAlignment":"","endMilepost":"2.52"}},"closure":{"closureID":"M217BA","logNumber":"1","closureTimestamp":{"closureRequestDate":"2020-01-15","closureRequestTime":"19:00:13","closureRequestEpoch":"1579143613","closureStartDate":"2020-01-21","closureStartTime":"09:01:00","closureStartEpoch":"1579626060","closureEndDate":"2020-01-21","closureEndTime":"14:30:00","closureEndEpoch":"1579645800","isClosureEndIndefinite":"false"},"facility":"Conventional Hwy","typeOfClosure":"Lane","typeOfWork":"Guardrail Work","durationOfClosure":"Standard","estimatedDelay":"6","lanesClosed":"2","totalExistingLanes":"2","isCHINReportable":"true","code1097":{"isCode1097":"false","code1097Timestamp":{"code1097Date":"","code1097Time":"","code1097Epoch":""}},"code1098":{"isCode1098":"false","code1098Timestamp":{"code1098Date":"","code1098Time":"","code1098Epoch":""}},"code1022":{"isCode1022":"false","code1022Timestamp":{"code1022Date":"","code1022Time":"","code1022Epoch":""}}}}},{"lcs":{"index":"M217BA-0002-2020-01-22-09:01:00","recordTimestamp":{"recordDate":"2020-01-20","recordTime":"07:31:06","recordEpoch":"1579534266"},"location":{"travelFlowDirection":"East","begin":{"beginDistrict":"5","beginLocationName":"Sandspit Road","beginFreeFormDescription":"with ramp","beginNearbyPlace":"Goleta","beginLongitude":"-119.832491","beginLatitude":"34.418770","beginElevation":"9","beginDirection":"","beginCounty":"Santa Barbara","beginRoute":"SR-217","beginRouteSuffix":"","beginPostmilePrefix":"","beginPostmile":"0.94","beginAlignment":"","beginMilepost":"0.48"},"end":{"endDistrict":"5","endLocationName":"Route 101","endFreeFormDescription":"","endNearbyPlace":"Santa Barbara","endLongitude":"-119.808635","endLatitude":"34.441932","endElevation":"88","endDirection":"","endCounty":"Santa Barbara","endRoute":"SR-217","endRouteSuffix":"","endPostmilePrefix":"","endPostmile":"2.99","endAlignment":"","endMilepost":"2.52"}},"closure":{"closureID":"M217BA","logNumber":"2","closureTimestamp":{"closureRequestDate":"2020-01-15","closureRequestTime":"19:00:32","closureRequestEpoch":"1579143632","closureStartDate":"2020-01-22","closureStartTime":"09:01:00","closureStartEpoch":"1579712460","closureEndDate":"2020-01-22","closureEndTime":"14:30:00","closureEndEpoch":"1579732200","isClosureEndIndefinite":"false"},"facility":"Conventional Hwy","typeOfClosure":"Lane","typeOfWork":"Guardrail Work","durationOfClosure":"Standard","estimatedDelay":"6","lanesClosed":"2","totalExistingLanes":"2","isCHINReportable":"true","code1097":{"isCode1097":"false","code1097Timestamp":{"code1097Date":"","code1097Time":"","code1097Epoch":""}},"code1098":{"isCode1098":"false","code1098Timestamp":{"code1098Date":"","code1098Time":"","code1098Epoch":""}},"code1022":{"isCode1022":"false","code1022Timestamp":{"code1022Date":"","code1022Time":"","code1022Epoch":""}}}}},{"lcs":{"index":"M217BA-0003-2020-01-22-09:01:00","recordTimestamp":{"recordDate":"2020-01-20","recordTime":"07:31:06","recordEpoch":"1579534266"},"location":{"travelFlowDirection":"East","begin":{"beginDistrict":"5","beginLocationName":"Hollister Avenue","beginFreeFormDescription":"","beginNearbyPlace":"Goleta","beginLongitude":"-119.817907","beginLatitude":"34.435377","beginElevation":"55","beginDirection":"","beginCounty":"Santa Barbara","beginRoute":"SR-217","beginRouteSuffix":"","beginPostmilePrefix":"","beginPostmile":"2.23","beginAlignment":"","beginMilepost":"1.77"},"end":{"endDistrict":"5","endLocationName":"Route 217","endFreeFormDescription":"","endNearbyPlace":"Goleta","endLongitude":"-119.817907","endLatitude":"34.435377","endElevation":"55","endDirection":"East","endCounty":"Santa Barbara","endRoute":"SR-217","endRouteSuffix":"","endPostmilePrefix":"","endPostmile":"2.23","endAlignment":"","endMilepost":"1.77"}},"closure":{"closureID":"M217BA","logNumber":"3","closureTimestamp":{"closureRequestDate":"2020-01-15","closureRequestTime":"19:02:20","closureRequestEpoch":"1579143740","closureStartDate":"2020-01-22","closureStartTime":"09:01:00","closureStartEpoch":"1579712460","closureEndDate":"2020-01-22","closureEndTime":"14:30:00","closureEndEpoch":"1579732200","isClosureEndIndefinite":"false"},"facility":"On Ramp","typeOfClosure":"Full","typeOfWork":"Guardrail Work","durationOfClosure":"Standard","estimatedDelay":"6","lanesClosed":"All","totalExistingLanes":"2","isCHINReportable":"false","code1097":{"isCode1097":"false","code1097Timestamp":{"code1097Date":"","code1097Time":"","code1097Epoch":""}},"code1098":{"isCode1098":"false","code1098Timestamp":{"code1098Date":"","code1098Time":"","code1098Epoch":""}},"code1022":{"isCode1022":"false","code1022Timestamp":{"code1022Date":"","code1022Time":"","code1022Epoch":""}}}}},{"lcs":{"index":"M217BA-0004-2020-01-21-09:01:00","recordTimestamp":{"recordDate":"2020-01-20","recordTime":"07:31:06","recordEpoch":"1579534266"},"location":{"travelFlowDirection":"East","begin":{"beginDistrict":"5","beginLocationName":"Hollister Avenue","beginFreeFormDescription":"","beginNearbyPlace":"Goleta","beginLongitude":"-119.817907","beginLatitude":"34.435377","beginElevation":"55","beginDirection":"","beginCounty":"Santa Barbara","beginRoute":"SR-217","beginRouteSuffix":"","beginPostmilePrefix":"","beginPostmile":"2.23","beginAlignment":"","beginMilepost":"1.77"},"end":{"endDistrict":"5","endLocationName":"Route 217","endFreeFormDescription":"","endNearbyPlace":"Goleta","endLongitude":"-119.817907","endLatitude":"34.435377","endElevation":"55","endDirection":"East","endCounty":"Santa Barbara","endRoute":"SR-217","endRouteSuffix":"","endPostmilePrefix":"","endPostmile":"2.23","endAlignment":"","endMilepost":"1.77"}},"closure":{"closureID":"M217BA","logNumber":"4","closureTimestamp":{"closureRequestDate":"2020-01-15","closureRequestTime":"19:02:35","closureRequestEpoch":"1579143755","closureStartDate":"2020-01-21","closureStartTime":"09:01:00","closureStartEpoch":"1579626060","closureEndDate":"2020-01-21","closureEndTime":"14:30:00","closureEndEpoch":"1579645800","isClosureEndIndefinite":"false"},"facility":"On Ramp","typeOfClosure":"Full","typeOfWork":"Guardrail Work","durationOfClosure":"Standard","estimatedDelay":"6","lanesClosed":"All","totalExistingLanes":"2","isCHINReportable":"false","code1097":{"isCode1097":"false","code1097Timestamp":{"code1097Date":"","code1097Time":"","code1097Epoch":""}},"code1098":{"isCode1098":"false","code1098Timestamp":{"code1098Date":"","code1098Time":"","code1098Epoch":""}},"code1022":{"isCode1022":"false","code1022Timestamp":{"code1022Date":"","code1022Time":"","code1022Epoch":""}}}}}]