[{"lcs":{"index":"M67IA-0001-2020-01-22-09:01:00","recordTimestamp":{"recordDate":"2020-01-22","recordTime":"17:32:37","recordEpoch":"1579743157"},"location":{"travelFlowDirection":"North","begin":{"beginDistrict":"11","beginLocationName":"Iron Mtn Dr","beginFreeFormDescription":"","beginNearbyPlace":"Poway","beginLongitude":"-116.971007","beginLatitude":"32.966633","beginElevation":"1476","beginDirection":"","beginCounty":"San Diego","beginRoute":"SR-67","beginRouteSuffix":"","beginPostmilePrefix":"","beginPostmile":"14.35","beginAlignment":"","beginMilepost":"13.82"},"end":{"endDistrict":"11","endLocationName":"","endFreeFormDescription":"JSO Poway Rd.","endNearbyPlace":"Poway","endLongitude":"-116.973357","endLatitude":"32.978531","endElevation":"1620","endDirection":"","endCounty":"San Diego","endRoute":"SR-67","endRouteSuffix":"","endPostmilePrefix":"","endPostmile":"15.20","endAlignment":"","endMilepost":"14.67"}},"closure":{"closureID":"M67IA","logNumber":"1","closureTimestamp":{"closureRequestDate":"2020-01-17","closureRequestTime":"10:38:52","closureRequestEpoch":"1579286332","closureStartDate":"2020-01-22","closureStartTime":"09:01:00","closureStartEpoch":"1579712460","closureEndDate":"2020-01-22","closureEndTime":"14:01:00","closureEndEpoch":"1579730460","isClosureEndIndefinite":"false"},"facility":"Mainline","typeOfClosure":"Lane","typeOfWork":"Guardrail Repair","durationOfClosure":"Standard","estimatedDelay":"Not Reported","lanesClosed":"2","totalExistingLanes":"2","isCHINReportable":"true","code1097":{"isCode1097":"true","code1097Timestamp":{"code1097Date":"2020-01-22","code1097Time":"08:56:03","code1097Epoch":"1579712163"}},"code1098":{"isCode1098":"false","code1098Timestamp":{"code1098Date":"","code1098Time":"","code1098Epoch":""}},"code1022":{"isCode1022":"false","code1022Timestamp":{"code1022Date":"","code1022Time":"","code1022Epoch":""}}}}}]